cancli/__init__.py
cancli/__main__.py
cancli/can_handler.py
cancli/can_setup.py
cancli/complete.sh
cancli/main.py
cancli/meta.py
cancli/parse_error_frame.py
cancli/runmodule.sh
cancli/utils.py
cancli-1.3.3.dist-info/entry_points.txt
cancli-1.3.3.dist-info/licenses/LICENSE
cancli-1.3.3.dist-info/WHEEL
cancli-1.3.3.dist-info/METADATA
cancli-1.3.3.dist-info/RECORD
