Metadata-Version: 2.4
Name: cancli
Version: 1.3.3
Summary: A command line interface to send and receive CAN bus messages.
Author-email: erzo <erzo@posteo.de>
Requires-Python: >=3.7
Classifier: Environment :: Console
Classifier: License :: OSI Approved :: BSD License
License-File: LICENSE
Requires-Dist: prompt_toolkit >= 3.0.43, < 4
Requires-Dist: confattr >= 1.6.0, < 2.0.0
Requires-Dist: python-can >= 4.0, < 5
Requires-Dist: cantools >= 39.0.0, < 40
Project-URL: Bug tracker, https://gitlab.com/erzo/cancli/-/issues
Project-URL: Change log, https://gitlab.com/erzo/cancli/-/tags
Project-URL: Documentation, https://gitlab.com/erzo/cancli/-/blob/master/README.md
Project-URL: Source code, https://gitlab.com/erzo/cancli
